setup.py
src/pipette/__init__.py
src/pipette/pipes.py
src/pipette.egg-info/PKG-INFO
src/pipette.egg-info/SOURCES.txt
src/pipette.egg-info/dependency_links.txt
src/pipette.egg-info/pbr.json
src/pipette.egg-info/requires.txt
src/pipette.egg-info/top_level.txt