Metadata-Version: 1.1
Name: pipette
Version: 0.1.9
Summary: A library implementing a protocol to simplify programming pipeline-like chains of intercommunicating processes.
Home-page: https://github.com/ewiger/pipette/
Author: Yauhen Yakimovich
Author-email: eugeny.yakimovitch@gmail.com
License: MIT
Download-URL: https://github.com/ewiger/pipette/tarball/master
Platform: UNKNOWN
Classifier: Topic :: Scientific/Engineering :: Information Analysis
Classifier: Intended Audience :: Developers
Classifier: Programming Language :: Python
Classifier: Topic :: Software Development :: Libraries :: Python Modules
Classifier: Development Status :: 5 - Production/Stable
Classifier: Operating System :: POSIX :: Linux
Classifier: Operating System :: MacOS
